MANIFEST.in
setup.cfg
setup.py
copyings/copying.exe.txt
copyings/copying.libjuman.txt
copyings/copying.libjuman.win.txt
dist/juman-7.01_ext_win32/lib/libjuman.so
dist/juman-7.01_ext_win64/dics/autodic/jumandic.dat
dist/juman-7.01_ext_win64/dics/autodic/jumandic.pat
dist/juman-7.01_ext_win64/dics/dic/JUMAN.connect
dist/juman-7.01_ext_win64/dics/dic/JUMAN.grammar
dist/juman-7.01_ext_win64/dics/dic/JUMAN.kankei
dist/juman-7.01_ext_win64/dics/dic/JUMAN.katuyou
dist/juman-7.01_ext_win64/dics/dic/jumandic.dat
dist/juman-7.01_ext_win64/dics/dic/jumandic.mat
dist/juman-7.01_ext_win64/dics/dic/jumandic.pat
dist/juman-7.01_ext_win64/dics/dic/jumandic.tab
dist/juman-7.01_ext_win64/dics/wikipediadic/jumandic.dat
dist/juman-7.01_ext_win64/dics/wikipediadic/jumandic.pat
dist/juman-7.01_ext_win64/lib/libjuman.so
juman-7.01/lib/connect.c
juman-7.01/lib/const.h
juman-7.01/lib/encoder.c
juman-7.01/lib/encoder.h
juman-7.01/lib/ext_api.c
juman-7.01/lib/ext_api.h
juman-7.01/lib/getid.c
juman-7.01/lib/grammar.c
juman-7.01/lib/iotool.c
juman-7.01/lib/japanese.c
juman-7.01/lib/juman.h
juman-7.01/lib/juman_lib.c
juman-7.01/lib/juman_pat.h
juman-7.01/lib/katuyou.c
juman-7.01/lib/lisp.c
juman-7.01/lib/pat.c
juman-7.01/lib/patfile.c
juman-7.01/lib/zentohan.c
jumany.egg-info/PKG-INFO
jumany.egg-info/SOURCES.txt
jumany.egg-info/dependency_links.txt
jumany.egg-info/top_level.txt
python_module/LICENSE.txt
python_module/README.rst
python_module/__init__.py
python_module/__main__.py
python_module/juman_ext.py
python_module/test/__init__.py
python_module/test/__main__.py
python_module/test/test_jumany.py
scripts/config.h
scripts/jumanrc.win
scripts/setup_ext.py